requeue/__init__.py
requeue-0.4.0.dist-info/LICENSE
requeue-0.4.0.dist-info/METADATA
requeue-0.4.0.dist-info/WHEEL
requeue-0.4.0.dist-info/RECORD
