Metadata-Version: 2.1
Name: requeue
Version: 0.4.0
Summary: An asynchronous queue for requesting data
Home-page: https://gitlab.com/deepadmax/requeue
License: GPL-3.0-or-later
Author: Maximillian Strand
Author-email: maxi@millian.se
Requires-Python: >=3.12,<4.0
Classifier: License :: OSI Approved :: GNU General Public License v3 or later (GPLv3+)
Classifier: Programming Language :: Python :: 3
Classifier: Programming Language :: Python :: 3.12
Project-URL: Repository, https://gitlab.com/deepadmax/requeue
